{
    "uid": "812836777645A14C3E8B67B3E033BC27809A",
    "lastModificationTime": null,
    "items": {
        "name": "Persistent Variables",
        "type": "persistent_variables",
        "numbers": [
            {
                "name": "My Per",
                "scope": 2,
                "index": 0
            }
        ],
        "strings": [
            {
                "name": "",
                "scope": 2,
                "index": 0
            }
        ],
        "booleans": [
            {
                "name": "",
                "scope": 2,
                "index": 0
            }
        ],
        "lists": [
            {
                "name": "",
                "index": 0,
                "scope": 0
            }
        ],
        "domain": "com.endlessIllusoft.showMessageScriptExtension"
    }
}